[ {
  "id" : 2,
  "pattern" : "added",
  "partsOfSpeech" : "VB",
  "index" : {
    "0" : [ "pair=Builders@en", "AllConf=0.301129234629862", "triple=e dbp:designation1Free3name Builders@en", "class=HistoricPlace" ],
    "1" : [ "pair=Design period@en", "AllConf=0.300498753117207", "triple=e dbp:beginningLabel Design period@en", "class=HistoricPlace" ]
  }
}, {
  "id" : 19,
  "pattern" : "born",
  "partsOfSpeech" : "VB",
  "index" : {
    "0" : [ "pair=Free agent@en", "AllConf=0.410633484162896", "triple=e dbp:currentTeam Free agent@en", "class=AmericanFootballPlayer" ],
    "1" : [ "pair=American@en", "AllConf=0.185053380782918", "triple=e dbp:nationality American@en", "class=Artist" ],
    "2" : [ "pair=Painting", "AllConf=0.14538419016031", "triple=e dbp:field Painting", "class=Artist" ],
    "3" : [ "pair=Twenty20", "AllConf=0.379970544918999", "triple=e dbp:column Twenty20", "class=Cricketer" ],
    "4" : [ "pair=One_Day_International", "AllConf=0.379347826086956", "triple=e dbp:column One_Day_International", "class=Cricketer" ],
    "5" : [ "pair=List_A_cricket", "AllConf=0.375052675937632", "triple=e dbp:column List_A_cricket", "class=Cricketer" ],
    "6" : [ "pair=@en", "AllConf=0.355108877721943", "triple=e dbp:year @en", "class=Cricketer" ],
    "7" : [ "pair=Right-arm medium@en", "AllConf=0.347467608951708", "triple=e dbp:bowling Right-arm medium@en", "class=Cricketer" ],
    "8" : [ "pair=&ndash;@en", "AllConf=0.339092872570194", "triple=e dbp:fivefor &ndash;@en", "class=Cricketer" ],
    "9" : [ "pair=&ndash;/&ndash;@en", "AllConf=0.337349397590361", "triple=e dbp:100s &ndash;/&ndash;@en", "class=Cricketer" ],
    "10" : [ "pair=n/a@en", "AllConf=0.331961591220851", "triple=e dbp:tenfor n/a@en", "class=Cricketer" ],
    "11" : [ "pair=–/–@en", "AllConf=0.329084588644264", "triple=e dbp:100s –/–@en", "class=Cricketer" ],
    "12" : [ "pair=Left-handed@en", "AllConf=0.321158690176322", "triple=e dbp:batting Left-handed@en", "class=Cricketer" ],
    "13" : [ "pair=\"Left-handed\"", "AllConf=0.318912237330037", "triple=e dbo:battingSide \"Left-handed\"", "class=Cricketer" ],
    "14" : [ "pair=England", "AllConf=0.315741583257507", "triple=e dbp:birthPlace England", "class=Cricketer" ],
    "15" : [ "pair=Right-handed@en", "AllConf=0.30299055613851", "triple=e dbp:batting Right-handed@en", "class=Cricketer" ],
    "16" : [ "pair=\"Right-handed\"", "AllConf=0.298761609907121", "triple=e dbo:battingSide \"Right-handed\"", "class=Cricketer" ],
    "17" : [ "pair=–@en", "AllConf=0.298013245033113", "triple=e dbp:tenfor –@en", "class=Cricketer" ],
    "18" : [ "pair=true@en", "AllConf=0.296514069718606", "triple=e dbp:international true@en", "class=Cricketer" ],
    "19" : [ "pair=Retired@en", "AllConf=0.715263518138262", "triple=e dbp:currentteam Retired@en", "class=Cyclist" ],
    "20" : [ "pair=Track_cycling", "AllConf=0.688172043010753", "triple=e dbp:discipline Track_cycling", "class=Cyclist" ],
    "21" : [ "pair=Sprinter@en", "AllConf=0.679738562091503", "triple=e dbp:ridertype Sprinter@en", "class=Cyclist" ],
    "22" : [ "pair=Road_bicycle_racing", "AllConf=0.59860788863109", "triple=e dbp:discipline Road_bicycle_racing", "class=Cyclist" ],
    "23" : [ "pair=Road@en", "AllConf=0.594629822732012", "triple=e dbp:discipline Road@en", "class=Cyclist" ],
    "24" : [ "pair=Italy", "AllConf=0.575431034482759", "triple=e dbp:birthPlace Italy", "class=Cyclist" ],
    "25" : [ "pair=Rider@en", "AllConf=0.551340559041643", "triple=e dbp:role Rider@en", "class=Cyclist" ],
    "26" : [ "pair=yes@en", "AllConf=0.539630836047774", "triple=e dbp:showMedals yes@en", "class=Cyclist" ],
    "27" : [ "pair=France", "AllConf=0.516703786191537", "triple=e dbp:birthPlace France", "class=Cyclist" ],
    "28" : [ "pair=solo_singer@en", "AllConf=0.111784511784512", "triple=e dbp:background solo_singer@en", "class=MusicalArtist" ],
    "29" : [ "pair=\"solo_singer\"", "AllConf=0.111148197596796", "triple=e dbo:background \"solo_singer\"", "class=MusicalArtist" ],
    "30" : [ "pair=Defender_(association_football)", "AllConf=0.341107871720117", "triple=e dbo:position Defender_(association_football)", "class=SoccerManager" ],
    "31" : [ "pair=Midfielder", "AllConf=0.339299030574198", "triple=e dbo:position Midfielder", "class=SoccerManager" ],
    "32" : [ "pair=Forward_(association_football)", "AllConf=0.321167883211679", "triple=e dbo:position Forward_(association_football)", "class=SoccerManager" ]
  }
}, {
  "id" : 23,
  "pattern" : "built",
  "partsOfSpeech" : "VB",
  "index" : {
    "0" : [ "pair=Private@en", "AllConf=0.112008072653885", "triple=e dbp:governingBody Private@en", "class=Building" ]
  }
}, {
  "id" : 34,
  "pattern" : "designed",
  "partsOfSpeech" : "VB",
  "index" : {
    "0" : [ "pair=Bertrand@en", "AllConf=0.855218855218855", "triple=e dbp:ref Bertrand@en", "class=Aircraft" ],
    "1" : [ "pair=Production completed@en", "AllConf=0.767857142857143", "triple=e dbp:status Production completed@en", "class=Aircraft" ],
    "2" : [ "pair=In production@en", "AllConf=0.622467771639042", "triple=e dbp:status In production@en", "class=Aircraft" ],
    "3" : [ "pair=one@en", "AllConf=0.611526147278549", "triple=e dbp:crew one@en", "class=Aircraft" ],
    "4" : [ "pair=one passenger@en", "AllConf=0.590909090909091", "triple=e dbp:capacity one passenger@en", "class=Aircraft" ]
  }
}, {
  "id" : 42,
  "pattern" : "formed",
  "partsOfSpeech" : "VB",
  "index" : {
    "0" : [ "pair=@en", "AllConf=0.135834411384217", "triple=e dbp:genre @en", "class=Band" ],
    "1" : [ "pair=group_or_band@en", "AllConf=0.103358905245698", "triple=e dbp:background group_or_band@en", "class=Band" ],
    "2" : [ "pair=\"group_or_band\"", "AllConf=0.102851848038711", "triple=e dbo:background \"group_or_band\"", "class=Band" ]
  }
}, {
  "id" : 45,
  "pattern" : "found",
  "partsOfSpeech" : "VB",
  "index" : {
    "0" : [ "pair=changed@en", "AllConf=0.12117212249208", "triple=e dbp:verifiedfields changed@en", "class=ChemicalCompound" ]
  }
}, {
  "id" : 63,
  "pattern" : "known",
  "partsOfSpeech" : "VB",
  "index" : {
    "0" : [ "pair=American@en", "AllConf=0.155871886120996", "triple=e dbp:nationality American@en", "class=Artist" ],
    "1" : [ "pair=Painting", "AllConf=0.131011608623549", "triple=e dbp:field Painting", "class=Artist" ],
    "2" : [ "pair=changed@en", "AllConf=0.15311510031679", "triple=e dbp:verifiedfields changed@en", "class=ChemicalCompound" ]
  }
}, {
  "id" : 66,
  "pattern" : "listed",
  "partsOfSpeech" : "VB",
  "index" : {
    "0" : [ "pair=Redundant_church", "AllConf=0.874538745387454", "triple=e dbp:functionalStatus Redundant_church", "class=HistoricBuilding" ]
  }
}, {
  "id" : 85,
  "pattern" : "produced",
  "partsOfSpeech" : "VB",
  "index" : {
    "0" : [ "pair=Bertrand@en", "AllConf=0.858585858585859", "triple=e dbp:ref Bertrand@en", "class=Aircraft" ],
    "1" : [ "pair=Production completed@en", "AllConf=0.741071428571429", "triple=e dbp:status Production completed@en", "class=Aircraft" ],
    "2" : [ "pair=In production@en", "AllConf=0.651933701657459", "triple=e dbp:status In production@en", "class=Aircraft" ]
  }
}, {
  "id" : 90,
  "pattern" : "published",
  "partsOfSpeech" : "VB",
  "index" : {
    "0" : [ "pair=Print@en", "AllConf=0.118468146027201", "triple=e dbp:mediaType Print@en", "class=Book" ],
    "1" : [ "pair=English@en", "AllConf=0.116314661769207", "triple=e dbp:language English@en", "class=Book" ],
    "2" : [ "pair=United States@en", "AllConf=0.115475255302435", "triple=e dbp:country United States@en", "class=Book" ],
    "3" : [ "pair=Hardcover", "AllConf=0.114652956298201", "triple=e dbo:mediaType Hardcover", "class=Book" ],
    "4" : [ "pair=First edition@en", "AllConf=0.114104595879556", "triple=e dbp:caption First edition@en", "class=Book" ]
  }
}, {
  "id" : 114,
  "pattern" : "used",
  "partsOfSpeech" : "VB",
  "index" : {
    "0" : [ "pair=changed@en", "AllConf=0.292433537832311", "triple=e dbp:watchedfields changed@en", "class=ChemicalCompound" ]
  }
} ]