[ {
  "id" : 2,
  "pattern" : "archdiocese",
  "partsOfSpeech" : "NN",
  "index" : {
    "0" : [ "pair=o", "MaxConf=1.0", "triple=e dbp:pastor o", "class=HistoricBuilding" ]
  }
}, {
  "id" : 3,
  "pattern" : "building",
  "partsOfSpeech" : "NN",
  "index" : {
    "0" : [ "pair=o", "MaxConf=1.0", "triple=e dbp:pastor o", "class=HistoricBuilding" ]
  }
}, {
  "id" : 5,
  "pattern" : "care",
  "partsOfSpeech" : "NN",
  "index" : {
    "0" : [ "pair=o", "MaxConf=1.0", "triple=e dbp:imagealt o", "class=HistoricBuilding" ]
  }
}, {
  "id" : 6,
  "pattern" : "catholic",
  "partsOfSpeech" : "NN",
  "index" : {
    "0" : [ "pair=o", "MaxConf=1.0", "triple=e dbp:pastor o", "class=HistoricBuilding" ]
  }
}, {
  "id" : 7,
  "pattern" : "church",
  "partsOfSpeech" : "NN",
  "index" : {
    "0" : [ "pair=o", "MaxConf=1.0", "triple=e dbp:pastor o", "class=HistoricBuilding" ]
  }
}, {
  "id" : 8,
  "pattern" : "churches",
  "partsOfSpeech" : "NN",
  "index" : {
    "0" : [ "pair=o", "MaxConf=1.0", "triple=e dbp:imagealt o", "class=HistoricBuilding" ]
  }
}, {
  "id" : 9,
  "pattern" : "conservation",
  "partsOfSpeech" : "NN",
  "index" : {
    "0" : [ "pair=o", "MaxConf=1.0", "triple=e dbp:imagealt o", "class=HistoricBuilding" ]
  }
}, {
  "id" : 11,
  "pattern" : "diocese",
  "partsOfSpeech" : "NN",
  "index" : {
    "0" : [ "pair=o", "MaxConf=1.0", "triple=e dbp:pastor o", "class=HistoricBuilding" ]
  }
}, {
  "id" : 12,
  "pattern" : "england",
  "partsOfSpeech" : "NN",
  "index" : {
    "0" : [ "pair=o", "MaxConf=1.0", "triple=e dbp:pastor o", "class=HistoricBuilding" ]
  }
}, {
  "id" : 14,
  "pattern" : "grade",
  "partsOfSpeech" : "NN",
  "index" : {
    "0" : [ "pair=o", "MaxConf=1.0", "triple=e dbp:imagealt o", "class=HistoricBuilding" ]
  }
}, {
  "id" : 15,
  "pattern" : "heritage",
  "partsOfSpeech" : "NN",
  "index" : {
    "0" : [ "pair=o", "MaxConf=1.0", "triple=e dbp:imagealt o", "class=HistoricBuilding" ]
  }
}, {
  "id" : 17,
  "pattern" : "list",
  "partsOfSpeech" : "NN",
  "index" : {
    "0" : [ "pair=o", "MaxConf=1.0", "triple=e dbp:imagealt o", "class=HistoricBuilding" ]
  }
}, {
  "id" : 20,
  "pattern" : "mary's",
  "partsOfSpeech" : "NN",
  "index" : {
    "0" : [ "pair=o", "MaxConf=1.0", "triple=e dbp:imagealt o", "class=HistoricBuilding" ]
  }
}, {
  "id" : 21,
  "pattern" : "miles",
  "partsOfSpeech" : "NN",
  "index" : {
    "0" : [ "pair=o", "MaxConf=1.0", "triple=e dbp:imagealt o", "class=HistoricBuilding" ]
  }
}, {
  "id" : 22,
  "pattern" : "national",
  "partsOfSpeech" : "NN",
  "index" : {
    "0" : [ "pair=o", "MaxConf=1.0", "triple=e dbp:imagealt o", "class=HistoricBuilding" ]
  }
}, {
  "id" : 23,
  "pattern" : "parish",
  "partsOfSpeech" : "NN",
  "index" : {
    "0" : [ "pair=o", "MaxConf=1.0", "triple=e dbp:pastor o", "class=HistoricBuilding" ]
  }
}, {
  "id" : 24,
  "pattern" : "part",
  "partsOfSpeech" : "NN",
  "index" : {
    "0" : [ "pair=o", "MaxConf=1.0", "triple=e dbp:pastor o", "class=HistoricBuilding" ]
  }
}, {
  "id" : 28,
  "pattern" : "road",
  "partsOfSpeech" : "NN",
  "index" : {
    "0" : [ "pair=o", "MaxConf=1.0", "triple=e dbp:imagealt o", "class=HistoricBuilding" ]
  }
}, {
  "id" : 29,
  "pattern" : "roman",
  "partsOfSpeech" : "NN",
  "index" : {
    "0" : [ "pair=o", "MaxConf=1.0", "triple=e dbp:pastor o", "class=HistoricBuilding" ]
  }
}, {
  "id" : 30,
  "pattern" : "stands",
  "partsOfSpeech" : "NN",
  "index" : {
    "0" : [ "pair=o", "MaxConf=1.0", "triple=e dbp:imagealt o", "class=HistoricBuilding" ]
  }
}, {
  "id" : 31,
  "pattern" : "states",
  "partsOfSpeech" : "NN",
  "index" : {
    "0" : [ "pair=o", "MaxConf=1.0", "triple=e dbp:pastor o", "class=HistoricBuilding" ]
  }
}, {
  "id" : 32,
  "pattern" : "trust",
  "partsOfSpeech" : "NN",
  "index" : {
    "0" : [ "pair=o", "MaxConf=1.0", "triple=e dbp:imagealt o", "class=HistoricBuilding" ]
  }
}, {
  "id" : 33,
  "pattern" : "united",
  "partsOfSpeech" : "NN",
  "index" : {
    "0" : [ "pair=o", "MaxConf=1.0", "triple=e dbp:pastor o", "class=HistoricBuilding" ]
  }
}, {
  "id" : 34,
  "pattern" : "village",
  "partsOfSpeech" : "NN",
  "index" : {
    "0" : [ "pair=o", "MaxConf=1.0", "triple=e dbp:imagealt o", "class=HistoricBuilding" ]
  }
} ]