[ {
  "id" : 6,
  "pattern" : "australian",
  "partsOfSpeech" : "JJ",
  "index" : {
    "0" : [ "pair=\"Australian\"@en", "Coherence=0.489", "triple=e dbp:nationality \"Australian\"@en", "class=HR_Athlete" ]
  }
}, {
  "id" : 15,
  "pattern" : "british",
  "partsOfSpeech" : "JJ",
  "index" : {
    "0" : [ "pair=\"British\"@en", "Coherence=0.472", "triple=e dbp:nationality \"British\"@en", "class=HR_Athlete" ]
  }
}, {
  "id" : 16,
  "pattern" : "canadian",
  "partsOfSpeech" : "JJ",
  "index" : {
    "0" : [ "pair=\"Canadian\"@en", "Coherence=0.498", "triple=e dbp:nationality \"Canadian\"@en", "class=HR_Athlete" ]
  }
}, {
  "id" : 22,
  "pattern" : "equestrian competed",
  "partsOfSpeech" : "JJ",
  "index" : {
    "0" : [ "pair=Equestrianism", "Coherence=0.446", "triple=e dbp:sport Equestrianism", "class=HR_Athlete" ]
  }
}, {
  "id" : 28,
  "pattern" : "french",
  "partsOfSpeech" : "JJ",
  "index" : {
    "0" : [ "pair=\"French\"@en", "Coherence=0.477", "triple=e dbp:nationality \"French\"@en", "class=HR_Athlete" ]
  }
}, {
  "id" : 29,
  "pattern" : "german",
  "partsOfSpeech" : "JJ",
  "index" : {
    "0" : [ "pair=\"German\"@en", "Coherence=0.496", "triple=e dbp:nationality \"German\"@en", "class=HR_Athlete" ]
  }
}, {
  "id" : 33,
  "pattern" : "hungarian",
  "partsOfSpeech" : "JJ",
  "index" : {
    "0" : [ "pair=\"Hungarian\"@en", "Coherence=0.492", "triple=e dbp:nationality \"Hungarian\"@en", "class=HR_Athlete" ]
  }
}, {
  "id" : 34,
  "pattern" : "italian",
  "partsOfSpeech" : "JJ",
  "index" : {
    "0" : [ "pair=\"Italian\"@en", "Coherence=0.491", "triple=e dbp:nationality \"Italian\"@en", "class=HR_Athlete" ],
    "1" : [ "pair=\"Italy\"@en", "Coherence=0.484", "triple=e dbp:country \"Italy\"@en", "class=HR_Athlete" ],
    "2" : [ "pair=Italy", "Coherence=0.475", "triple=e dbp:birthPlace Italy", "class=HR_Athlete" ]
  }
}, {
  "id" : 35,
  "pattern" : "japanese",
  "partsOfSpeech" : "JJ",
  "index" : {
    "0" : [ "pair=\"Japanese\"@en", "Coherence=0.481", "triple=e dbp:nationality \"Japanese\"@en", "class=HR_Athlete" ]
  }
}, {
  "id" : 37,
  "pattern" : "korean",
  "partsOfSpeech" : "JJ",
  "index" : {
    "0" : [ "pair=\"South Korean\"@en", "Coherence=0.493", "triple=e dbp:nationality \"South Korean\"@en", "class=HR_Athlete" ]
  }
}, {
  "id" : 45,
  "pattern" : "middle-distance",
  "partsOfSpeech" : "JJ",
  "index" : {
    "0" : [ "pair=\"Middle-distance running\"@en", "Coherence=0.5", "triple=e dbp:sport \"Middle-distance running\"@en", "class=HR_Athlete" ]
  }
}, {
  "id" : 49,
  "pattern" : "polish",
  "partsOfSpeech" : "JJ",
  "index" : {
    "0" : [ "pair=\"Polish\"@en", "Coherence=0.494", "triple=e dbp:nationality \"Polish\"@en", "class=HR_Athlete" ]
  }
}, {
  "id" : 62,
  "pattern" : "south\u001Ckorean",
  "partsOfSpeech" : "JJ",
  "index" : {
    "0" : [ "pair=\"South Korean\"@en", "Coherence=0.478", "triple=e dbp:nationality \"South Korean\"@en", "class=HR_Athlete" ]
  }
}, {
  "id" : 63,
  "pattern" : "south korean",
  "partsOfSpeech" : "JJ",
  "index" : {
    "0" : [ "pair=\"South Korean\"@en", "Coherence=0.493", "triple=e dbp:nationality \"South Korean\"@en", "class=HR_Athlete" ]
  }
}, {
  "id" : 64,
  "pattern" : "spanish",
  "partsOfSpeech" : "JJ",
  "index" : {
    "0" : [ "pair=\"Spanish\"@en", "Coherence=0.486", "triple=e dbp:nationality \"Spanish\"@en", "class=HR_Athlete" ]
  }
}, {
  "id" : 68,
  "pattern" : "swiss",
  "partsOfSpeech" : "JJ",
  "index" : {
    "0" : [ "pair=\"Swiss\"@en", "Coherence=0.488", "triple=e dbp:nationality \"Swiss\"@en", "class=HR_Athlete" ]
  }
} ]